nxcl/__init__.py
nxcl/config/__init__.py
nxcl/config/argparse.py
nxcl/core/__init__.py
nxcl/core/config/__init__.py
nxcl/core/config/base.py
nxcl/core/config/utils.py
nxcl/core/config/yaml.py
nxcl/core/misc/__init__.py
nxcl/core/misc/module.py
nxcl/experimental/__init__.py
nxcl/experimental/experiment.py
nxcl/experimental/utils.py
nxcl/logging/__init__.py
nxcl/logging/handler/__init__.py
nxcl/logging/handler/rich.py
nxcl/logging/handler/tqdm.py
nxcl/rich/__init__.py
nxcl/rich/logging.py
nxcl/rich/progress.py
nxcl/utils/__init__.py
nxcl-0.0.3.dev3.dist-info/LICENSE
nxcl-0.0.3.dev3.dist-info/METADATA
nxcl-0.0.3.dev3.dist-info/WHEEL
nxcl-0.0.3.dev3.dist-info/top_level.txt
nxcl-0.0.3.dev3.dist-info/zip-safe
nxcl-0.0.3.dev3.dist-info/RECORD
