Metadata-Version: 2.1
Name: nxcl
Version: 0.0.3.dev3
Summary: NXCL is an eXperiment Core Library
Home-page: https://github.com/yuneg11/nxcl
Author: EungGu Yun
Author-email: yuneg11@gmail.com
License: MIT license
Project-URL: Documentation, https://yuneg11.github.io/NXCL
Project-URL: Source, https://github.com/yuneg11/nxcl
Project-URL: Tracker, https://github.com/yuneg11/nxcl/issues
Keywords: nxcl,NXCL
Classifier: Operating System :: OS Independent
Classifier: License :: OSI Approved :: MIT License
Classifier: Programming Language :: Python :: 3
Classifier: Programming Language :: Python :: 3.7
Classifier: Programming Language :: Python :: 3.8
Classifier: Programming Language :: Python :: 3.9
Classifier: Programming Language :: Python :: 3.10
Classifier: Topic :: Software Development :: Libraries :: Python Modules
Classifier: Topic :: System :: Logging
Requires-Python: >=3.7
License-File: LICENSE
